tensordash/Keras-MNIST.py
tensordash/fastdash.py
tensordash/tensordash.py
tensordash/torchdash.py
tensor_dash-1.8.1.dist-info/LICENSE
tensor_dash-1.8.1.dist-info/METADATA
tensor_dash-1.8.1.dist-info/WHEEL
tensor_dash-1.8.1.dist-info/top_level.txt
tensor_dash-1.8.1.dist-info/RECORD
