Metadata-Version: 2.1
Name: tensor-dash
Version: 1.8.1
Summary: A python package that lets you remotely monitor your deep learning training metrics through it's companion app.
Home-page: https://github.com/CleanPegasus/TensorDash
Author-email: hmhmrock@gmail.com, arunk609@gmail.com
License: MIT
Platform: UNKNOWN
Classifier: Programming Language :: Python :: 3
Classifier: Programming Language :: Python :: 3.7
Requires-Dist: requests
